zerotwo/__init__.py
zerotwo/franxx.py
zerotwo/parastie/pistil.py
zerotwo/parastie/stamen.py
zero_two-0.1.1.dist-info/WHEEL
zero_two-0.1.1.dist-info/METADATA
zero_two-0.1.1.dist-info/RECORD
