Metadata-Version: 2.1
Name: zero-two
Version: 0.1.1
Summary: Zero Two
Author: Michael Kim
Author-email: kim.michael95@gmail.com
Requires-Python: >=3.6,<4.0
Classifier: Operating System :: OS Independent
Classifier: Programming Language :: Python :: 3
Classifier: Programming Language :: Python :: 3.6
Classifier: Programming Language :: Python :: 3.7
Classifier: Programming Language :: Python :: 3.8
Classifier: Programming Language :: Python :: 3.9
